Workbook
Name FechaControl: '[1]Tabla (H)'!$P$6:$P$25
Name ImpactoRiesgo: 'Información'!$I$9:$K$9
Name ListaFechas: #REF!
Name ProbabilidadRiesgo: 'Información'!$H$6:$H$8
Name EstadoRiesgos: 'Información'!$B$18:$B$21
Name MatrizRiesgo: 'Información'!$I$6:$K$8
Name Criticidad: 'Información'!$B$4:$B$6
Name Estado: 'Información'!$B$9:$B$12
Name PrioridadRiesgo: 'Información'!$H$6:$H$8
Name ListaFechas: #REF!

Sheet Información
O2: Ejemplo
B3: Tabla de Criticidad | P3: Se ve con una lista (ProbabilidadRiesgo) | Q3: Se ve con una lista (ImpactoRiesgo)
B4: Alto | C4: 3 | G4: Matriz de Riesgos - Criticidad | O4: Criticidad | P4: Probabilidad | Q4: Impacto
B5: Medio | C5: 2 | H5: Probabilidad | O5: {=INDEX(MatrizRiesgo,MATCH(P5,ProbabilidadRiesgo,0),MATCH(Q5,ImpactoRiesgo,0))} -> 1 | P5: Alta | Q5: Alto
B6: Bajo | C6: 1 | H6: Alta | I6: 4 | J6: 2 | K6: 1 | O6: {=INDEX(MatrizRiesgo,MATCH(P6,ProbabilidadRiesgo,0),MATCH(Q6,ImpactoRiesgo,0))} -> 3 | P6: Media | Q6: Alto
H7: Media | I7: 7 | J7: 5 | K7: 3 | O7: {=INDEX(MatrizRiesgo,MATCH(P7,ProbabilidadRiesgo,0),MATCH(Q7,ImpactoRiesgo,0))} -> 9 | P7: Baja | Q7: Bajo
B8: Estado | H8: Baja | I8: 9 | J8: 8 | K8: 6 | O8: {=INDEX(MatrizRiesgo,MATCH(P8,ProbabilidadRiesgo,0),MATCH(Q8,ImpactoRiesgo,0))} -> 7 | P8: Media | Q8: Bajo
B9: Abierto | I9: Bajo | J9: Medio | K9: Alto | L9: Impacto | O9: {=INDEX(MatrizRiesgo,MATCH(P9,ProbabilidadRiesgo,0),MATCH(Q9,ImpactoRiesgo,0))} -> 4 | P9: Alta | Q9: Bajo
B10: Cerrado | O10: {=INDEX(MatrizRiesgo,MATCH(P10,ProbabilidadRiesgo,0),MATCH(Q10,ImpactoRiesgo,0))} -> 7 | P10: Media | Q10: Bajo
B11: Eliminado | O11: {=INDEX(MatrizRiesgo,MATCH(P11,ProbabilidadRiesgo,0),MATCH(Q11,ImpactoRiesgo,0))} -> 9 | P11: Baja | Q11: Bajo
B12: Problema | G12: Tratamiento de Riesgos - Acciones | O12: {=INDEX(MatrizRiesgo,MATCH(P12,ProbabilidadRiesgo,0),MATCH(Q12,ImpactoRiesgo,0))} -> 4 | P12: Alta | Q12: Bajo
G13: Criticidad = Impacto * Probabilidad
G14: 1, 2 y 3 | H14: : Mayor prioridad, atención obligada, acción inmediata
G15: 4, 5, 6, 7 y 8 | H15: : Prioridad media, decidir entre:
H16: Plan de mitigación, si relación costo/beneficio es adecuada
B17: Estado Riesgos | H17: Plan de contingencia, si relación costo/beneficio no es adecuada
B18: Pendiente | G18: 9 | H18: Baja prioridad y monitorear Riesgo
B19: Cerrado
B20: Eliminado
B21: Problema

Sheet Información del Documento
A1: Titulo Organización | B1: VAYO Solutions SPA
A2: Nombre proyecto | B2: ElTinySaaS
A3: Fecha | B3: 46093
A5: Información del documento
A6: <Incorporara una breve descrición del contenido del documento, >
A7: Nombre Archivo
A8: Registro de Riesgos.XLS
A10: Historial Estructura Documento
A11: Fecha | B11: Autor / Responsable | C11: Versión | D11: Descripción
A12: 42074 | B12: Gestión de Proyectos y Calidad | C12: 1.0 | D12: Versión Inicial
A15: Historial Contenido Documento y Bitácora
A16: Fecha | B16: Autor / Responsable | C16: Versión | D16: Descripción
A17: 46109 | B17: Jorge Escobar | C17: 1.1 | D17: Documento Inicial
A18: 46109 | B18: Jorge Escobar | C18: 1.2 | D18: Se agregan riesgos 3, 4
A19: 46109 | B19: Jorge Escobar | C19: 1.3 | D19: Se elimina riesgos 2,3,4. Se agrega riesgo 5
A20: 46109 | B20: Jorge Escobar | C20: 1.4 | D20: Se baja probabilidad a riesgo 1
A21: 46109 | B21: Jorge Escobar | C21: 1.5 | D21: se agregan riesgos 6, 7, 8, 9

Sheet Matriz
D4: Impacto
C5: Probabilidad | D5: Muy Bajo | E5: Bajo | F5: Medio | G5: Alto | H5: Muy Alto
C6: Muy Alto | D6: Medio | E6: Alto | F6: Alto | G6: Muy Alto | H6: Muy Alto
C7: Alto | D7: Medio | E7: Medio | F7: Alto | G7: Muy Alto | H7: Muy Alto
C8: Medio | D8: Bajo | E8: Medio | F8: Alto | G8: Alto | H8: Muy Alto
C9: Bajo | D9: Bajo | E9: Bajo | F9: Medio | G9: Alto | H9: Alto
C10: Muy Bajo | D10: Bajo | E10: Bajo | F10: Medio | G10: Medio | H10: Alto

Sheet Matriz de Riesgos
A2: ID | B2: Fecha Creación | C2: Tipo | D2: Riesgo (Evento) | E2: Causa | F2: Efecto | G2: Probabilidad Ocurrencia | H2: Impacto | I2: Probabilidad (numérico) | J2: Impacto (numérico) | K2: Criticidad | L2: Respuesta | M2: Responsable | N2: Fecha de Compromiso | O2: Estado | P2: Comentarios
A3: 1 | B3: 46109 | C3: Técnico | D3: Perdida de documentacion critica del proyecto | E3: Ausencia de respaldos, errores humanos, corrupcion de archivos, falla en credenciales de acceso | F3: Pérdida de registros vitales para el desarrollo del proyecto yperdida de coerencia entre entregas | G3: medio | H3: Muy Alto | I3: 2 | J3: 5 | K3: Muy Alto | L3: Mitigar: implementar respaldos automáticos y control de versiones de todos los archivos | M3: Equipo Backend | N3: 46127 | O3: Pendiente | P3: Realizar chequeos regulares a los archivos criticos
A4: 2 | B4: 46109 | C4: Técnico | D4: Personal de desarrollo con falta de conocimientos tecnicos | E4: Falta de conocimientos en tecnologías, arquitectura o integración | F4: Retrasos, errores técnicos y retrabajo | G4: Alto | H4: Muy Alto | I4: 3 | J4: 5 | K4: Muy Alto | L4: Mitigar: capacitar al equipo y asignar tareas según nivel de experiencia | M4: Líder Técnico | N4: 46124 | O4: Pendiente | P4: Priorizar tecnologías conocidas
A5: 3 | B5: 46109 | C5: Calendario | D5: Retraso en el levantamiento de requerimientos | E5: Baja disponibilidad del cliente o del equipo | F5: Demora en el diseño y desarrollo del proyecto | G5: Alto | H5: Alto | I5: 2 | J5: 4 | K5: Alto | L5: Mitigar: planificar reuniones y validar requerimientos tempranamente | M5: Equipo Desarrollo | N5: 46122 | O5: Pendiente | P5: Mantener actas de reunión
A6: 4 | B6: 46109 | C6: Gestión | D6: Problemas de comunicación entre integrantes del equipo | E6: Falta de coordinación y seguimiento de tareas | F6: Inconsistencias, duplicidad de trabajo y retrasos | G6: Alto | H6: Alto | I6: 2 | J6: 4 | K6: Alto | L6: Mitigar: realizar reuniones semanales y utilizar herramientas colaborativas | M6: Equipo Desarrollo | N6: 46120 | O6: Pendiente | P6: Definir claramente roles y tareas
A7: 5 | B7: 46109 | C7: Técnico | D7: Corrupción o incompatibilidad entre versiones del software | E7: Cambios simultáneos sin control de versiones adecuado | F7: Fallas en el sistema y pérdida de avances | G7: Alto | H7: Muy Alto | I7: 2 | J7: 5 | K7: Muy Alto | L7: Mitigar: utilizar Git y definir un flujo de ramas de trabajo | M7: Equipo Desarrollo | N7: 46132 | O7: Pendiente | P7: Establecer revisiones antes de fusionar cambios
A8: 6 | B8: 46109 | C8: Seguridad | D8: Vulnerabilidades de seguridad en el sistema | E8: Falta de validaciones, permisos o controles de acceso | F8: Robo, modificación o filtración de datos | G8: Medio | H8: Muy Alto | I8: 3 | J8: 5 | K8: Muy Alto | L8: Mitigar: implementar autenticación, roles y validación de datos | M8: Equipo Backend | N8: 46157 | O8: Pendiente | P8: Revisar accesos al panel administrador
A9: 7 | B9: 46109 | C9: Costos | D9: Problemas de presupuesto por factores externos | E9: Aumento en costos de hosting, dominio, herramientas o infraestructura | F9: Limitación del alcance o retrasos en despliegue | G9: Medio | H9: Alto | I9: 3 | J9: 4 | K9: Alto | L9: Mitigar: considerar margen de contingencia y alternativas gratuitas | M9: Equipo General | N9: 46152 | O9: Pendiente | P9: Revisar presupuesto periódicamente
A10: 8 | B10: 46109 | C10: Calidad | D10: Falta de pruebas funcionales antes de la entrega | E10: Poco tiempo asignado a la fase de testing por presión de plazos | F10: Dificultad al verificar al estabilidad del producto | G10: Medio | H10: Alto | I10: 3 | J10: 4 | K10: Alto | L10: Mitigar: revisar constantemente lso plazos de entrega y definir pruebas prioritarias | M10: Equipo General | N10: 46162 | O10: Pendiente | P10: Verificar que pruebas se concretaron
A11: 9 | B11: 46109 | C11: Técnico | D11: Fallas en la integración entre frontend y backend | E11: Diferencias en la lógica implementada por distintos integrantes | F11: Errores en formularios, consultas y módulos del sistema | G11: Medio | H11: Alto | I11: 3 | J11: 4 | K11: Alto | L11: Mitigar: documentar APIs y validar estructura de datos antes de desarrollar | M11: Equipo Desarrollo | N11: 46160 | O11: Pendiente | P11: Realizar pruebas de integración frecuentes
A12: 10 | B12: 46109 | C12: Gestión | D12: Acumulación de deuda técnica | E12: Equipo sin experiencia calibrando sprints y velocidad en etapas iniciales | F12: Retraso en hitos y presentación final | G12: Alto | H12: Muy Alto | I12: 2 | J12: 5 | K12: Muy Alto | L12: Mitigar: dividir tareas grandes en subtareas y monitorear avances | M12: Equipo Desarrollo | N12: 46142 | O12: Pendiente | P12: Revisar cronograma semanalmente
A13: 11 | B13: 46109 | C13: Técnico | D13: Fallas en el cálculo de cotizaciones y ventas | E13: Errores en fórmulas o lógica de negocio | F13: Información incorrecta para clientes y empresa | G13: Medio | H13: Muy Alto | I13: 3 | J13: 5 | K13: Muy Alto | L13: Mitigar: validar cálculos con múltiples casos de prueba | M13: Equipo Backend | N13: 46154 | O13: Pendiente | P13: Revisar reglas de negocio con el cliente
A14: 12 | B14: 46109 | C14: Calidad | D14: Requerimientos mal interpretados por el equipo | E14: Levantamiento incompleto o mala comunicación con el cliente | F14: Desarrollo de funciones que no cumplen las necesidades reales | G14: Medio | H14: Muy Alto | I14: 3 | J14: 5 | K14: Muy Alto | L14: Mitigar: validar requerimientos mediante reuniones y prototipos | M14: Product Owner | N14: 46127 | O14: Pendiente | P14: Solicitar aprobación de funcionalidades
... A27: 25 | B27: 46114 | C27: Calidad | D27: Dependencia del integrante senior | E27: Brecha de habilidades entre los miembros del equipo es notorial a la hora de desarrollar | F27: Dependecia total del avance del proyecto de un integrante | G27: Alto | H27: Alto | I27: 4 | J27: 4 | K27: Muy Alto | L27: Mitigar: Distribucion de tareas y incentivar el aprendisaje entre los miembros del equipo para que ganen experiencia y durante el desarrolo | M27: Equipo desarrollo | N27: 46135 | O27: Pendiente | P27: Registrar el avance de cada miembro

Sheet Matriz Impacto y Probabilidad
D4: Impacto
C5: Probabilidad | D5: Muy Bajo | E5: Bajo | F5: Medio | G5: Alto | H5: Muy Alto
C6: Muy Alto | D6: Medio | E6: Alto | F6: Alto | G6: Muy Alto | H6: Muy Alto
C7: Alto | D7: Medio | E7: Medio | F7: Alto | G7: Muy Alto | H7: Muy Alto
C8: Medio | D8: Bajo | E8: Medio | F8: Alto | G8: Alto | H8: Muy Alto
C9: Bajo | D9: Bajo | E9: Bajo | F9: Medio | G9: Alto | H9: Alto
C10: Muy Bajo | D10: Bajo | E10: Bajo | F10: Medio | G10: Medio | H10: Alto

Sheet Matriz Registro de Riesgos Exam
A1: Registro de Riesgos
A2: ID | B2: Fecha Creación | C2: Tipo | D2: Riesgo (Evento) | E2: Causa | F2: Efecto | G2: Probabilidad Ocurrencia | H2: Impacto | I2: probabilidad | J2: impacto | K2: Criticidad | L2: Respuesta (Evitar, Transferir, Mitigar) | M2: Responsable | N2: Fecha de Compromiso | O2: Estado | P2: Comentarios
A3: 1 | B3: 46093 | C3: Técnico | D3: Corrupción entre versiones de SW. | E3: Software se podría corromper debido a administración inadecuada de la configuración, múltiples versiones de desarrollo y/o testing. | F3: Calidad | G3: Muy Alto | H3: Muy Alto | I3: =IF(G3="muy alto",1,IF(G3="alto",2,IF(G3="medio",3,IF(G3="bajo",4,5)))) -> 1 | J3: =IF(H3="muy alto",5,IF(H3="alto",4,IF(H3="medio",3,IF(H3="bajo",2,1)))) -> 5 | K3: {=INDEX(Matriz!$D$6:$H$10,I3,J3)} -> Muy Alto | L3: Evitar: 1) Postergar Mejoras complejas hasta fin proyecto. 2) Examinar por un comité los nuevos requerimientos, categorizar en funcionales / No funcionales 3)Uso de plan de mejora, en base a plan contratado por cliente. | M3: LG | N3: 42898 | O3: Pendiente
A4: 2 | B4: 46094 | C4: Calendario | D4: Cierre tardío de revisión del levantamiento | E4: Se planificó cierre del levantamiento para 30 de Marzo, se estima que se extenderá hasta segunda semana Abril | F4: Plazo | G4: Muy Alto | H4: Alto | I4: =IF(G4="muy alto",1,IF(G4="alto",2,IF(G4="medio",3,IF(G4="bajo",4,5)))) -> 1 | J4: =IF(H4="muy alto",5,IF(H4="alto",4,IF(H4="medio",3,IF(H4="bajo",2,1)))) -> 4 | K4: {=INDEX(Matriz!$D$6:$H$10,I4,J4)} -> Muy Alto | L4: Mitigar: -Se dividió la tarea de revisión en dos grandes Requerimiento. - el primero se cierre 07 de Abril, el segundo se cierra 13 de Abril | M4: LG | N4: 42902 | O4: Eliminado
A5: 3 | B5: 46094 | C5: Calendario | D5: Adjudicación tardía a proveedor tecnológico | E5: Se estimó que el equipo de trabajo debería iniciar el 19 de Abril, pero cierre tardío de definiciones impide generar adjudicacion de provedoor para dominio web | F5: Plazo | G5: Alto | H5: Muy Alto | I5: =IF(G5="muy alto",1,IF(G5="alto",2,IF(G5="medio",3,IF(G5="bajo",4,5)))) -> 2 | J5: =IF(H5="muy alto",5,IF(H5="alto",4,IF(H5="medio",3,IF(H5="bajo",2,1)))) -> 5 | K5: {=INDEX(Matriz!$D$6:$H$10,I5,J5)} -> Muy Alto | L5: Mitigar: -Se reprograma incio para el 1 de Mayo - se acuerda de manera interna - se publicará con lo cerrado hasta la fecha 16 de mayo - despriorizar desarrollo de mantenedores | M5: LG | N5: 31-05-2017 | O5: Eliminado
A6: 4 | B6: 46094 | C6: Costos | D6: Falla en presupuesto de servidor para desarrollo de proyecto | E6: Presupuesto podría ser no acorde a los precios del mercado por el plazo y necesidades que implica la ejecución | F6: Costo | G6: Medio | H6: Alto | I6: =IF(G6="muy alto",1,IF(G6="alto",2,IF(G6="medio",3,IF(G6="bajo",4,5)))) -> 3 | J6: =IF(H6="muy alto",5,IF(H6="alto",4,IF(H6="medio",3,IF(H6="bajo",2,1)))) -> 4 | K6: {=INDEX(Matriz!$D$6:$H$10,I6,J6)} -> Alto | L6: Mitigar: - - Limitar alcance de Proyecto - Mejorar rendimiento de sistema de archivos, mediante script de pruebas - Definir planes de almacenamiento, acorde a necesidad de operacional | O6: Eliminado
A7: 5 | B7: 46095 | C7: Calendario | D7: Cierre de hitos del proyecto fuera de plazo | E7: Debido Poca disponibilidad de los usuarios funcionales. | F7: Plazo | G7: Alto | H7: Muy Alto | I7: =IF(G7="muy alto",1,IF(G7="alto",2,IF(G7="medio",3,IF(G7="bajo",4,5)))) -> 2 | J7: =IF(H7="muy alto",5,IF(H7="alto",4,IF(H7="medio",3,IF(H7="bajo",2,1)))) -> 5 | K7: {=INDEX(Matriz!$D$6:$H$10,I7,J7)} -> Muy Alto | L7: Mitigar: Enviar gantt a usuarios para que se programen | M7: JG | N7: 42895 | O7: Eliminado | P7: se generó OC para tercer ingeniero
A8: 6 | B8: 46096 | C8: Equipo de Trabajo | D8: Menos profesionales para etapa de desarrollo | E8: Equipo de desarrollo carece de personal | F8: Plazo | G8: Medio | H8: Muy Alto | I8: =IF(G8="muy alto",1,IF(G8="alto",2,IF(G8="medio",3,IF(G8="bajo",4,5)))) -> 3 | J8: =IF(H8="muy alto",5,IF(H8="alto",4,IF(H8="medio",3,IF(H8="bajo",2,1)))) -> 5 | K8: {=INDEX(Matriz!$D$6:$H$10,I8,J8)} -> Muy Alto | L8: Mitigar: Analista de interfaz del proyecto considera adelantar requerimientos funcionales y maqueta de interfaz, antes del 29 de Mayo | O8: Pendiente
A9: 7 | B9: 46097 | C9: Equipo de Trabajo | D9: Cambio en la arquitectura del Proyecto | E9: Debido al analisis funcional, se modifica framework de desarrollo para Agente IA | F9: Plazo | G9: Medio | H9: Muy Alto | I9: =IF(G9="muy alto",1,IF(G9="alto",2,IF(G9="medio",3,IF(G9="bajo",4,5)))) -> 3 | J9: =IF(H9="muy alto",5,IF(H9="alto",4,IF(H9="medio",3,IF(H9="bajo",2,1)))) -> 5 | K9: {=INDEX(Matriz!$D$6:$H$10,I9,J9)} -> Muy Alto | L9: Mitigar: Evaluar comportamiento nuevo FW | O9: Pendiente | P9: Asume la Jefatura del Proyecto, el gerente de proyectos de TINET, quien participo como Jefe de Proyecto en el anteproyecto (podría ser una oportunidad).
A10: 8 | B10: 46098 | C10: Calendario | D10: No iniciar puesta en marcha en la fecha establecida | E10: (7 días de atraso en inicio de pruebas del servidor principal) | F10: Plazo | G10: Muy Bajo | H10: Muy Alto | I10: =IF(G10="muy alto",1,IF(G10="alto",2,IF(G10="medio",3,IF(G10="bajo",4,5)))) -> 5 | J10: =IF(H10="muy alto",5,IF(H10="alto",4,IF(H10="medio",3,IF(H10="bajo",2,1)))) -> 5 | K10: {=INDEX(Matriz!$D$6:$H$10,I10,J10)} -> Alto | L10: Mitigar: Instalar laboratorio para aislar a funcionarios que realizarán las pruebas, permitiendo mayor focalización y eficiencia, con el fin de reducir periodo de pruebas. | O10: Pendiente
A11: 9 | B11: 46099 | C11: Equipo de Trabajo | D11: No contar con pruebas funcionales de sistemas para pruebas Unitarias | E11: Retraso en maqueta funcional, debido a bajo personal disponible para desarrollo de pruebas unitarias | F11: Plazo | G11: Medio | H11: Muy Alto | I11: =IF(G11="muy alto",1,IF(G11="alto",2,IF(G11="medio",3,IF(G11="bajo",4,5)))) -> 3 | J11: =IF(H11="muy alto",5,IF(H11="alto",4,IF(H11="medio",3,IF(H11="bajo",2,1)))) -> 5 | K11: {=INDEX(Matriz!$D$6:$H$10,I11,J11)} -> Muy Alto | L11: Mitigar: Considerar pruebas periodicas funcionales, para mitigar retraso en pruebas funcionales de sistemas | O11: Pendiente
C26: Técnico | F26: Costo | G26: Muy Alto | H26: Muy Alto | O26: Pendiente
C27: Seguridad | F27: Plazo | G27: Alto | H27: Alto | O27: Cerrado
C28: Equipo de Trabajo | F28: Alcance | G28: Medio | H28: Medio | O28: Eliminado
C29: Calendario | F29: Calidad | G29: Bajo | H29: Bajo | O29: Problema
C30: Costos | G30: Muy Bajo | H30: Muy Bajo
C31: Clientes y Stakeholders
